[
    {
        "titulo": "camareros en la Cala de Mijas",
        "descripcion": "Restaurante de nueva apertura en La Cala Mijas busca camareros y camareras con experiencia demostrable dominio de inglés y español",
        "enlace": "688418520"
    },
    {
        "titulo": "Diseñador Gráfico",
        "descripcion": "Se busca diseñador con experiencia en Adobe Photoshop e Illustrator.",
        "enlace": "#"
    },
    {
        "titulo": "Community Manager",
        "descripcion": "Buscamos un profesional para gestionar redes sociales y crear contenido.",
        "enlace": "#"
    }
]